[{
  "_id": {
    "$oid": "64a6cab10e3976df2b2c2bd7"
  },
  "name": "Sebastião Alves",
  "link": "https://github.com/TiagoRato13/sebastiao_alves",
  "image": "https://res.cloudinary.com/datglss57/image/upload/v1686657230/myCV/Projects/Screenshot_2023-06-13_114912_fcxizv.png",
  "technology": [
    "PHP",
    "SQL",
    "HTML",
    "CSS",
    "Javascript"
  ],
  "createdAt": {
    "$date": "2023-07-06T14:07:45.987Z"
  },
  "updatedAt": {
    "$date": "2023-07-06T14:07:45.987Z"
  },
  "__v": 0
},
{
  "_id": {
    "$oid": "64a6caba0e3976df2b2c2bd9"
  },
  "name": "The boss at the end of the tunnel",
  "link": "https://tiagorato13.github.io/TheBossAtTheEndOfTheTunnel/",
  "image": "https://res.cloudinary.com/datglss57/image/upload/v1684402675/myCV/Projects/Screenshot_2023-05-18_103517_rvhscu.png",
  "technology": [
    "Javascript",
    "HTML",
    "CSS"
  ],
  "createdAt": {
    "$date": "2023-07-06T14:07:54.644Z"
  },
  "updatedAt": {
    "$date": "2023-07-06T14:07:54.644Z"
  },
  "__v": 0
},
{
  "_id": {
    "$oid": "64a6cac40e3976df2b2c2bdb"
  },
  "name": "Precoce",
  "link": "https://precoce.cyclic.app/",
  "image": "https://res.cloudinary.com/datglss57/image/upload/v1686653573/myCV/Projects/Screenshot_2023-06-13_115213_yzdtgi.png",
  "technology": [
    "Javascript",
    "Handlebars",
    "Node.Js",
    "Express",
    "MongoDB",
    "Bootstrap",
    "Postman",
    "Git",
    "GitHub",
    "HTML",
    "CSS"
  ],
  "createdAt": {
    "$date": "2023-07-06T14:08:04.715Z"
  },
  "updatedAt": {
    "$date": "2023-07-06T14:08:04.715Z"
  },
  "__v": 0
},
{
  "_id": {
    "$oid": "64a6cad00e3976df2b2c2bdd"
  },
  "name": "Maria Luísa Psicologia",
  "link": "https://marialuisasilvapsicologia.com/",
  "image": "https://res.cloudinary.com/datglss57/image/upload/v1684412634/myCV/Projects/Screenshot_2023-05-18_132259_jjh4qk.png",
  "technology": [
    "React",
    "Node.Js",
    "Express",
    "MongoDB",
    "Bootstrap",
    "Postman",
    "Git",
    "GitHub",
    "HTML",
    "CSS"
  ],
  "createdAt": {
    "$date": "2023-07-06T14:08:16.405Z"
  },
  "updatedAt": {
    "$date": "2023-07-06T14:08:16.405Z"
  },
  "__v": 0
},
{
  "_id": {
    "$oid": "64a6caf20e3976df2b2c2bdf"
  },
  "name": "Tiago Rato CV/Portfolio",
  "link": "https://tiagorato.vercel.app",
  "image": "https://res.cloudinary.com/datglss57/image/upload/v1688467671/myCV/Projects/Screenshot_2023-07-04_114508_c48i6q.png",
  "technology": [
    "React",
    "Node.Js",
    "Express",
    "MongoDB",
    "Docker",
    "Postman",
    "Git",
    "GitHub",
    "HTML",
    "CSS",
    "Cloudinary"
  ],
  "createdAt": {
    "$date": "2023-07-06T14:08:50.945Z"
  },
  "updatedAt": {
    "$date": "2023-07-06T14:08:50.945Z"
  },
  "__v": 0
}]